algoaccess/__init__.py
algoaccess/main.py
algoaccess-0.0.1.dist-info/LICENSE
algoaccess-0.0.1.dist-info/METADATA
algoaccess-0.0.1.dist-info/WHEEL
algoaccess-0.0.1.dist-info/top_level.txt
algoaccess-0.0.1.dist-info/RECORD
