Metadata-Version: 2.1
Name: algoaccess
Version: 0.0.1
Summary: AlgoAccess Python SDK
Home-page: https://github.com/algoaccess/algoaccess-python
Author: AlgoAccess
Author-email: admin@algoaccess.io
Project-URL: Bug Tracker, https://github.com/pypa/sampleproject/issues
Classifier: Programming Language :: Python :: 3
Classifier: License :: OSI Approved :: MIT License
Classifier: Operating System :: OS Independent
Requires-Python: >=3.6
License-File: LICENSE
Provides-Extra: build
Requires-Dist: 0.10.0 ; extra == 'build'
Provides-Extra: certifi
Requires-Dist: 2022.12.7 ; extra == 'certifi'
Provides-Extra: charset-normalizer
Requires-Dist: 3.1.0 ; extra == 'charset-normalizer'
Provides-Extra: colorama
Requires-Dist: 0.4.6 ; extra == 'colorama'
Provides-Extra: funkify
Requires-Dist: 0.4.4 ; extra == 'funkify'
Provides-Extra: idna
Requires-Dist: 3.4 ; extra == 'idna'
Provides-Extra: packaging
Requires-Dist: 23.0 ; extra == 'packaging'
Provides-Extra: pyproject_hooks
Requires-Dist: 1.0.0 ; extra == 'pyproject_hooks'
Provides-Extra: requests
Requires-Dist: 2.28.2 ; extra == 'requests'
Provides-Extra: tomli
Requires-Dist: 2.0.1 ; extra == 'tomli'
Provides-Extra: typing_extensions
Requires-Dist: 4.5.0 ; extra == 'typing_extensions'
Provides-Extra: urllib3
Requires-Dist: 1.26.15 ; extra == 'urllib3'
Provides-Extra: xtyping
Requires-Dist: 0.6.2 ; extra == 'xtyping'
